nonebot_plugin_revoke/__init__.py
nonebot_plugin_revoke/utils.py
nonebot_plugin_revoke-0.1.2.dist-info/METADATA
nonebot_plugin_revoke-0.1.2.dist-info/WHEEL
nonebot_plugin_revoke-0.1.2.dist-info/RECORD
